chatflow/__init__.py
chatflow/chat_flow.py
promptai/__init__.py
promptai/prompt_ai.py
prompt_ai-0.2.3.dist-info/METADATA
prompt_ai-0.2.3.dist-info/WHEEL
prompt_ai-0.2.3.dist-info/top_level.txt
prompt_ai-0.2.3.dist-info/RECORD
