Metadata-Version: 2.2
Name: prompt-ai
Version: 0.2.3
Summary: Prompt-AI is a Python library that automates the process of generating AI-powered newsletters. It scrapes content from a given URL, generates a structured newsletter using Google's Gemini API, and provides features for parsing content, sending emails, and creating blog page links.
Home-page: https://github.com/Gaurav-Codetek/chatflow.git
Author: Gaurav Patel (CodersTek)
Author-email: gauravpatel29@outlook.in
License: MIT
Keywords: python,chatbot,genai,generative ai,gemini api,chat ai
Classifier: Programming Language :: Python :: 3
Classifier: License :: OSI Approved :: MIT License
Classifier: Operating System :: OS Independent
Requires-Python: >=3.6
Requires-Dist: google.genai
Requires-Dist: requests
Requires-Dist: beautifulsoup4
Dynamic: author
Dynamic: author-email
Dynamic: classifier
Dynamic: description
Dynamic: description-content-type
Dynamic: home-page
Dynamic: keywords
Dynamic: license
Dynamic: requires-dist
Dynamic: requires-python
Dynamic: summary
